infravision/__init__.py
infravision-0.0.2.dist-info/METADATA
infravision-0.0.2.dist-info/WHEEL
infravision-0.0.2.dist-info/top_level.txt
infravision-0.0.2.dist-info/RECORD
