Metadata-Version: 2.4
Name: infravision
Version: 0.0.2
Summary: vision infrastructure
Author-email: Thomas Hansen <thomas@roboflow.com>
Classifier: Development Status :: 1 - Planning
Classifier: Programming Language :: Python :: 3
Classifier: License :: OSI Approved :: MIT License
Requires-Python: >=3.7
